MANIFEST.in
README.rst
setup.cfg
setup.py
django_sorted_autocomplete_m2m.egg-info/PKG-INFO
django_sorted_autocomplete_m2m.egg-info/SOURCES.txt
django_sorted_autocomplete_m2m.egg-info/dependency_links.txt
django_sorted_autocomplete_m2m.egg-info/pbr.json
django_sorted_autocomplete_m2m.egg-info/requires.txt
django_sorted_autocomplete_m2m.egg-info/top_level.txt
sorted_autocomplete_m2m/__init__.py
sorted_autocomplete_m2m/models.py
sorted_autocomplete_m2m/urls.py
sorted_autocomplete_m2m/views.py
sorted_autocomplete_m2m/widgets.py
sorted_autocomplete_m2m/static/sorted-autocomplete-m2m/css/m2m.css
sorted_autocomplete_m2m/static/sorted-autocomplete-m2m/js/m2m.js
sorted_autocomplete_m2m/templates/sorted-autocomplete-m2m/m2m.html