Metadata-Version: 1.1
Name: django-sorted-autocomplete-m2m
Version: 1.0.5
Summary: ManyToMany widget with autocomplete and sortable items.
Home-page: https://nixa.ca/
Author: Simon Lessnick
Author-email: simon@nixa.ca
License: MIT
Download-URL: https://github.com/nixaio/django-sorted-autocomplete-m2m/tarball/1.0.5
Keywords: django,manytomany,m2m,auto complete,autocomplete,sort,sorted,widget
Platform: UNKNOWN
